pyautossh.py
pyautossh-0.3.1.dist-info/METADATA
pyautossh-0.3.1.dist-info/WHEEL
pyautossh-0.3.1.dist-info/entry_points.txt
pyautossh-0.3.1.dist-info/licenses/LICENSE
pyautossh-0.3.1.dist-info/RECORD
