Metadata-Version: 2.4
Name: pyautossh
Version: 0.3.1
Summary: Automatically reconnect SSH sessions
License-Expression: MIT
License-File: LICENSE
Requires-Python: >=3.9
Provides-Extra: dev
Requires-Dist: mypy>=1.14.1; extra == 'dev'
